LICENSE
MANIFEST.in
README.rst
setup.py
django_thjwt.egg-info/PKG-INFO
django_thjwt.egg-info/SOURCES.txt
django_thjwt.egg-info/dependency_links.txt
django_thjwt.egg-info/top_level.txt
thjwt/__init__.py
thjwt/admin.py
thjwt/apps.py
thjwt/middleware.py
thjwt/models.py
thjwt/tests.py
thjwt/urls.py
thjwt/utils.py
thjwt/views.py
thjwt/migrations/0001_initial.py
thjwt/migrations/__init__.py