Metadata-Version: 1.1
Name: django-thjwt
Version: 0.1
Summary: A simple django app to use th-icloud web platform,
Home-page: https://www.th-icloud.cn
Author: JiaZiao & TianYang
Author-email: jiaza@nscc-tj.cn
License: BSD License
Platform: UNKNOWN
Classifier: Environment :: Web Environment
Classifier: Framework :: Django
Classifier: Framework :: Django :: 1.11
Classifier: Intended Audience :: Developers
Classifier: License :: OSI Approved :: BSD License
Classifier: Operating System :: OS Independent
Classifier: Programming Language :: Python :: 2.7
Classifier: Topic :: Internet :: WWW/HTTP
Classifier: Topic :: Internet :: WWW/HTTP :: Dynamic Content
